{
  "provider": "wikimedia_commons",
  "title": "File:Buddy Guy 1983.jpg",
  "original_url": "https://upload.wikimedia.org/wikipedia/commons/9/9d/Buddy_Guy_1983.jpg",
  "page_url": "https://commons.wikimedia.org/wiki/File:Buddy_Guy_1983.jpg",
  "width": 3512,
  "height": 2736,
  "mime_type": "image/jpeg",
  "thumbnail_url": "https://upload.wikimedia.org/wikipedia/commons/thumb/9/9d/Buddy_Guy_1983.jpg/960px-Buddy_Guy_1983.jpg",
  "creator": "Bubba73",
  "credit": "Own work",
  "description": "Buddy Guy, 1983, Urbana, Illinois",
  "date": "1983",
  "license_name": "CC BY-SA 3.0",
  "license_url": "https://creativecommons.org/licenses/by-sa/3.0",
  "usage_terms": "Creative Commons Attribution-Share Alike 3.0",
  "attribution_required": true,
  "score": 0.0,
  "identity_confidence": 0.0,
  "artist_id": 930,
  "artist_name": "buddy guy",
  "artist_slug": "buddy_guy",
  "search_query": "\"Buddy Guy\" blues guitarist",
  "discovered_via": "wikimedia_commons",
  "discovery_url": "",
  "approved": true,
  "approved_at": "2026-07-19T15:30:05.042667+00:00",
  "approved_image": "003-buddy-guy-1983.jpg",
  "storage_bucket": "historical-images",
  "storage_key": "artists/b/buddy_guy/photos/003-buddy-guy-1983.jpg",
  "storage_bytes": 3864588,
  "storage_content_type": "image/jpeg"
}
