{
  "provider": "wikimedia_commons",
  "title": "File:Metallica at The O2 Arena London 2008.jpg",
  "original_url": "https://upload.wikimedia.org/wikipedia/commons/0/07/Metallica_at_The_O2_Arena_London_2008.jpg",
  "page_url": "https://commons.wikimedia.org/wiki/File:Metallica_at_The_O2_Arena_London_2008.jpg",
  "width": 1785,
  "height": 1359,
  "mime_type": "image/jpeg",
  "thumbnail_url": "https://upload.wikimedia.org/wikipedia/commons/thumb/0/07/Metallica_at_The_O2_Arena_London_2008.jpg/960px-Metallica_at_The_O2_Arena_London_2008.jpg",
  "creator": "Kreepin Deth",
  "credit": "Own work",
  "description": "Metallica live at The O2 Arena, London, England",
  "date": "2008-09-15",
  "license_name": "CC BY 3.0",
  "license_url": "https://creativecommons.org/licenses/by/3.0",
  "usage_terms": "Creative Commons Attribution 3.0",
  "attribution_required": true,
  "score": 0.0,
  "identity_confidence": 0.0,
  "artist_id": 370,
  "artist_name": "metallica",
  "artist_slug": "metallica",
  "search_query": "\"Metallica\" heavy metal band",
  "discovered_via": "wikimedia_commons",
  "discovery_url": "",
  "approved": true,
  "approved_at": "2026-07-20T01:29:12.013814+00:00",
  "approved_image": "005-metallica-at-the-o2-arena-london-2008.jpg",
  "storage_bucket": "historical-images",
  "storage_key": "artists/m/metallica/photos/005-metallica-at-the-o2-arena-london-2008.jpg",
  "storage_bytes": 1458999,
  "storage_content_type": "image/jpeg"
}
