{
  "provider": "wikimedia_commons",
  "title": "File:Ed Sheeran-6826.jpg",
  "original_url": "https://upload.wikimedia.org/wikipedia/commons/0/00/Ed_Sheeran-6826.jpg",
  "page_url": "https://commons.wikimedia.org/wiki/File:Ed_Sheeran-6826.jpg",
  "width": 4206,
  "height": 4206,
  "mime_type": "image/jpeg",
  "thumbnail_url": "https://upload.wikimedia.org/wikipedia/commons/thumb/0/00/Ed_Sheeran-6826.jpg/960px-Ed_Sheeran-6826.jpg",
  "creator": "Harald Krichel",
  "credit": "Own work",
  "description": "Singer-songwriter Ed Sheeran at the 68th Berlin International Film Festival 2018",
  "date": "2018-02-23",
  "license_name": "CC BY-SA 3.0",
  "license_url": "https://creativecommons.org/licenses/by-sa/3.0",
  "usage_terms": "Creative Commons Attribution-Share Alike 3.0",
  "attribution_required": true,
  "score": 0.0,
  "identity_confidence": 0.0,
  "artist_id": 408,
  "artist_name": "ed sheeran",
  "artist_slug": "ed_sheeran",
  "search_query": "\"Ed Sheeran\" singer songwriter",
  "discovered_via": "wikimedia_commons",
  "discovery_url": "",
  "approved": true,
  "approved_at": "2026-07-19T22:32:24.029277+00:00",
  "approved_image": "005-ed-sheeran-6826.jpg",
  "storage_bucket": "historical-images",
  "storage_key": "artists/e/ed_sheeran/photos/005-ed-sheeran-6826.jpg",
  "storage_bytes": 13693845,
  "storage_content_type": "image/jpeg"
}
