{
  "collections": [
    {
      "collection_name": "Soft Rock Love Songs",
      "tracks": [
        {
          "rank": 1,
          "track_name": "Waiting for a Girl Like You",
          "artist_name": "Foreigner",
          "album_name": "4",
          "year_released": 1981,
          "fit_reason": "A heartfelt ballad that captures longing and anticipation in a smooth soft rock style."
        },
        {
          "rank": 2,
          "track_name": "How Deep Is Your Love",
          "artist_name": "Bee Gees",
          "album_name": "Saturday Night Fever",
          "year_released": 1977,
          "fit_reason": "Silky harmonies and tender lyrics make it one of the defining soft rock love songs."
        }
      ]
    }
  ]
}